{
  "input_folder": [
    "src",
    "test"
  ],
  "input_filter": [],
  "output_folder": "dist",
  "libs": [
    {
      "url": "https://github.com/open-abap/open-abap-core"
    },
    {
      "url": "https://github.com/open-abap/open-abap-bal"
    },
    {
      "folder": "/oras-artifacts/abap-bw",
      "files": "/src/**/*"
    }
  ],
  "write_unit_tests": true,
  "write_source_map": true,
  "options": {
    "ignoreSyntaxCheck": false,
    "skipReposrc": true,
    "extraSetup": "",
    "addFilenames": true,
    "addCommonJS": true,
    "unknownTypes": "runtimeError",
    "skip": []
  }
}